nanograph_sdk/__init__.py
nanograph_sdk/core/__init__.py
nanograph_sdk/core/asset_resolver.py
nanograph_sdk/core/asset_uploader.py
nanograph_sdk/core/asset_utils.py
nanograph_sdk/core/file_watcher.py
nanograph_sdk/core/interfaces.py
nanograph_sdk/core/logger.py
nanograph_sdk/core/message_handler.py
nanograph_sdk/core/node_executor.py
nanograph_sdk/core/node_registry.py
nanograph_sdk/core/resource_manager.py
nanograph_sdk/core/sdk.py
nanograph_sdk/core/server.py
nanograph_sdk/types/__init__.py
nanograph_sdk/types/assets.py
nanograph_sdk/types/protocol.py
nanograph_sdk/utils/__init__.py
nanograph_sdk-0.1.22.dist-info/METADATA
nanograph_sdk-0.1.22.dist-info/WHEEL
nanograph_sdk-0.1.22.dist-info/RECORD
