Metadata-Version: 2.4
Name: nanograph-sdk
Version: 0.1.22
Summary: Official Python SDK for Nanograph
Project-URL: Homepage, https://github.com/nanograph/sdk-py
Project-URL: Documentation, https://github.com/nanograph/sdk-py
Project-URL: Repository, https://github.com/nanograph/sdk-py.git
Project-URL: Bug Tracker, https://github.com/nanograph/sdk-py/issues
Author-email: Nanograph <anthony@volted.ai>
License-Expression: MIT
Keywords: nanograph,python,sdk
Classifier: Development Status :: 4 - Beta
Classifier: Intended Audience :: Developers
Classifier: License :: OSI Approved :: MIT License
Classifier: Programming Language :: Python :: 3
Classifier: Programming Language :: Python :: 3.8
Classifier: Programming Language :: Python :: 3.9
Classifier: Programming Language :: Python :: 3.10
Classifier: Programming Language :: Python :: 3.11
Requires-Python: >=3.8
Requires-Dist: aiofiles>=0.8
Requires-Dist: aiohttp>=3.8.0
Requires-Dist: watchdog>=2.0
Requires-Dist: websockets>=10.0
